IntelligentStockMarketAPI/__init__.py
IntelligentStockMarketAPI/api_client.py
IntelligentStockMarketAPI/configuration.py
IntelligentStockMarketAPI/exceptions.py
IntelligentStockMarketAPI/rest.py
IntelligentStockMarketAPI/api/__init__.py
IntelligentStockMarketAPI/api/eod_api.py
IntelligentStockMarketAPI/api/exchanges_api.py
IntelligentStockMarketAPI/api/financial_news_api.py
IntelligentStockMarketAPI/api/fundamentals_api.py
IntelligentStockMarketAPI/api/options_api.py
IntelligentStockMarketAPI/api/sentiment_api.py
IntelligentStockMarketAPI/api/stocks_api.py
IntelligentStockMarketAPI/models/__init__.py
IntelligentStockMarketAPI/models/address_response.py
IntelligentStockMarketAPI/models/analyst.py
IntelligentStockMarketAPI/models/annual_balance_sheet.py
IntelligentStockMarketAPI/models/annual_balance_sheet_response.py
IntelligentStockMarketAPI/models/balance_sheet.py
IntelligentStockMarketAPI/models/balance_sheets.py
IntelligentStockMarketAPI/models/contract_response.py
IntelligentStockMarketAPI/models/contracts.py
IntelligentStockMarketAPI/models/eod_stock.py
IntelligentStockMarketAPI/models/eod_stock_list_response.py
IntelligentStockMarketAPI/models/eod_stock_response.py
IntelligentStockMarketAPI/models/exchange.py
IntelligentStockMarketAPI/models/exchange_list_response.py
IntelligentStockMarketAPI/models/exchange_listed_companies_response.py
IntelligentStockMarketAPI/models/exchange_listed_stock.py
IntelligentStockMarketAPI/models/exchange_request.py
IntelligentStockMarketAPI/models/exchange_response.py
IntelligentStockMarketAPI/models/exchange_with_listed_tickers.py
IntelligentStockMarketAPI/models/exchange_with_tickers.py
IntelligentStockMarketAPI/models/general.py
IntelligentStockMarketAPI/models/general_address.py
IntelligentStockMarketAPI/models/general_contact.py
IntelligentStockMarketAPI/models/general_listings.py
IntelligentStockMarketAPI/models/general_officers.py
IntelligentStockMarketAPI/models/general_response.py
Intelligent_Stock_Market_API-0.0.6.dist-info/METADATA
Intelligent_Stock_Market_API-0.0.6.dist-info/WHEEL
Intelligent_Stock_Market_API-0.0.6.dist-info/top_level.txt
Intelligent_Stock_Market_API-0.0.6.dist-info/RECORD
