Metadata-Version: 2.1
Name: Intelligent-Stock-Market-API
Version: 0.0.6
Summary: An Intelligent EOD Stock Market, Financial News & Financial Social Media Trends API
Home-page: https://eod-stock-api.site
Author: MJ API Development
Author-email: support@eod-stock-api.site
License: Apache 2.0
Project-URL: Documentation, https://github.com/MJ-API-Development/stock-api-pythonsdk
Project-URL: Source, https://github.com/MJ-API-Development/stock-api-pythonsdk
Project-URL: Tracker, https://github.com/MJ-API-Development/stock-api-pythonsdk/issues
Project-URL: Subscribe - API Keys, https://eod-stock-api.site/login#signup
Project-URL: Intelligent Stock Market API, https://eod-stock-api.site
Project-URL: API Gateway, https://gateway.eod-stock-api.site
Keywords: OpenAPI,Intelligent EOD Stock Market API,EOD STOCK API,Financial News API,Financial Social Media Trends
Requires-Python: >=3.7
Requires-Dist: urllib3 (>=1.15)
Requires-Dist: six (>=1.10)
Requires-Dist: certifi
Requires-Dist: python-dateutil
